Metadata-Version: 2.1
Name: nmdb
Version: 0.1.8
Summary: Python examples to access data from the Neutron Monitor database
Author-email: "Christian T. Steigies" <steigies@nmdb.eu>
Maintainer-email: "Christian T. Steigies" <steigies@nmdb.eu>
License: Copyright (C) 2008-2024 Christian T. Steigies <steigies@nmdb.eu>
Project-URL: Homepage, https://nmdb.eu
Project-URL: Source, https://cau-git.rz.uni-kiel.de/ieap/ieap_public/et-public/ep-public/nmdb_public/
Keywords: cosmic rays,database
Classifier: Development Status :: 3 - Alpha
Classifier: Intended Audience :: Developers
Classifier: Topic :: Scientific/Engineering :: Physics
Classifier: License :: OSI Approved :: GNU General Public License v3 or later (GPLv3+)
Classifier: Programming Language :: Python :: 3
Classifier: Programming Language :: Python :: 3.9
Classifier: Programming Language :: Python :: 3.10
Classifier: Programming Language :: Python :: 3.11
Classifier: Programming Language :: Python :: 3.12
Classifier: Programming Language :: Python :: 3 :: Only
Requires-Python: >=3.9
License-File: LICENSE.txt
Requires-Dist: configparser
Requires-Dist: datetime
Requires-Dist: mysql
Requires-Dist: pandas
Requires-Dist: seaborn
Requires-Dist: SQLAlchemy
Provides-Extra: dev
Requires-Dist: check-manifest; extra == "dev"
Provides-Extra: test
Requires-Dist: coverage; extra == "test"
